ghostbot/__init__.py
ghostbot/dashboard.py
ghostbot/diagnose.py
ghostbot/inspector.py
ghostbot/main.py
ghostbot/repository.py
ghostbot/scheduler.py
ghostbot/shell.py
ghostbot/wizard.py
ghostbot/core/__init__.py
ghostbot/core/agent.py
ghostbot/core/asserter.py
ghostbot/core/basis.py
ghostbot/core/container.py
ghostbot/core/native_agent.py
ghostbot/core/native_container.py
ghostbot/core/native_reactor.py
ghostbot/core/reactor.py
ghostbot/core/scenario.py
ghostbot/core/web_agent.py
ghostbot/core/web_container.py
ghostbot/core/web_reactor.py
ghostbot/scripts/__init__.py
ghostbot/scripts/drivers/__init__.py
ghostbot/scripts/drivers/ghost.py
ghostbot/scripts/extensions/__init__.py
ghostbot/scripts/extensions/agents/__init__.py
ghostbot/scripts/extensions/agents/redmine_agent.py
ghostbot/scripts/extensions/agents/slack_agent.py
ghostbot/scripts/extensions/containers/__init__.py
ghostbot/scripts/extensions/containers/redmine_container.py
ghostbot/scripts/extensions/containers/slack_container.py
ghostbot/scripts/extensions/reactors/__init__.py
ghostbot/scripts/extensions/reactors/redmine_reactor.py
ghostbot/scripts/extensions/reactors/slack_reactor.py
ghostbot/scripts/updaters/__init__.py
ghostbot/scripts/updaters/agents/__init__.py
ghostbot/scripts/updaters/agents/chrome_agent.py
ghostbot/scripts/updaters/agents/firefox_agent.py
ghostbot/scripts/updaters/containers/__init__.py
ghostbot/scripts/updaters/containers/chrome_container.py
ghostbot/scripts/updaters/containers/firefox_container.py
ghostbot/scripts/updaters/reactors/__init__.py
ghostbot/scripts/updaters/reactors/chrome_reactor.py
ghostbot/scripts/updaters/reactors/firefox_reactor.py
ghostbot/utils/__init__.py
ghostbot/utils/archiver.py
ghostbot/utils/cli.py
ghostbot/utils/database.py
ghostbot/utils/datetime.py
ghostbot/utils/decorator.py
ghostbot/utils/excel.py
ghostbot/utils/json.py
ghostbot/utils/logger.py
ghostbot/utils/network.py
ghostbot/utils/os.py
ghostbot-0.1.0.dist-info/DESCRIPTION.rst
ghostbot-0.1.0.dist-info/METADATA
ghostbot-0.1.0.dist-info/RECORD
ghostbot-0.1.0.dist-info/WHEEL
ghostbot-0.1.0.dist-info/metadata.json
ghostbot-0.1.0.dist-info/top_level.txt
